{"3632":"npm run start me5218","14320":"npm run start me914","14832":"npm run start me599","17464":"npm run start me374","17716":"npm run start me513","17756":"npm run start me829","19108":"npm run start me909","22668":"npm run start me8880","23444":"npm run start me202","24492":"npm run start me1933","30088":"npm run start me408","30116":"npm run start me882","32748":"npm run start me956","32956":"npm run start me952","39604":"npm run start me816","41224":"npm run start me521","41472":"npm run start me936","42160":"npm run start me189","43904":"npm run start me340","44316":"npm run start me103","44496":"npm run start me606","48772":"npm run start me655","54488":"npm run start me347","54816":"npm run start me127","56156":"npm run start me33","56856":"npm run start me232","60168":"npm run start me191","61700":"npm run start me568","63944":"npm run start me214","64820":"npm run start me687","64860":"npm run start me755","65464":"npm run start me156","66380":"npm run start me62","70208":"npm run start me5307","75564":"npm run start me611","76652":"npm run start me254","77212":"npm run start me199","77948":"npm run start me9829","79628":"npm run start me733","79740":"npm run start me292","80308":"npm run start me786","81212":"npm run start me958","84968":"npm run start me815","85952":"npm run start me954","89504":"npm run start me626","90692":"npm run start me336","91576":"npm run start me398","97700":"npm run start me334","98080":"npm run start me2361","101096":"npm run start me65","104112":"npm run start me48","106668":"npm run start me597","107576":"npm run start me266","108292":"npm run start me934","108684":"npm run start me97","110784":"npm run start me288","111740":"npm run start me231","116308":"npm run start me5290","117468":"npm run start me706","119348":"npm run start me696","122000":"npm run start me7","122528":"npm run start me186","123344":"npm run start me992","129564":"npm run start me580","130164":"npm run start me939","130896":"npm run start me106","131672":"npm run start me722","133544":"npm run start me2","133940":"npm run start me7111","141672":"npm run start me61","142552":"npm run start me4564","145476":"npm run start me293","148888":"npm run start me238","152152":"npm run start me690","152236":"npm run start me518","155928":"npm run start me550","161276":"npm run start me870","161300":"npm run start me13","162608":"npm run start me712","166204":"npm run start me371","167240":"npm run start me461","167364":"npm run start me315","173596":"npm run start me373","178196":"npm run start me707","178828":"npm run start me760","179472":"npm run start me734","182088":"npm run start me573","184144":"npm run start me25","187348":"npm run start me564","190236":"npm run start me1856","190604":"npm run start me770","190824":"npm run start me1539","191360":"npm run start me451","191532":"npm run start me548","191688":"npm run start me153","193900":"npm run start me92","194388":"npm run start me474","195012":"npm run start me148","195660":"npm run start me769","196484":"npm run start me851","197472":"npm run start me987","197784":"npm run start me686","198772":"npm run start me905","200628":"npm run start me932","200780":"npm run start me552","201096":"npm run start me314","201384":"npm run start me327","203928":"npm run start me695","205716":"npm run start me5816","205792":"npm run start me354","206272":"npm run start me747","208380":"npm run start me358"}